nobar/__init__.py
nobar/nobar.py
nobar-1.0.2.17.dist-info/LICENSE
nobar-1.0.2.17.dist-info/METADATA
nobar-1.0.2.17.dist-info/WHEEL
nobar-1.0.2.17.dist-info/top_level.txt
nobar-1.0.2.17.dist-info/RECORD
