Metadata-Version: 2.1
Name: nobar
Version: 1.0.2.17
Summary: Usefull progress "bar"
Home-page: https://github.com/NoromTin/nobar
Author: NoromTin
Author-email: aninelo@gmail.com
Project-URL: Documentation, https://github.com/NoromTin/nobar/blob/main/README.md
Keywords: progress bar
Classifier: Programming Language :: Python :: 3
Classifier: License :: OSI Approved :: GNU General Public License v3 (GPLv3)
Classifier: Operating System :: OS Independent
Requires-Python: >=3.0
License-File: LICENSE
Requires-Dist: requests >=2.25.1
